odoo/addons/partner_bank_sort_code/README.rst
odoo/addons/partner_bank_sort_code/__init__.py
odoo/addons/partner_bank_sort_code/__manifest__.py
odoo/addons/partner_bank_sort_code/i18n/partner_bank_sort_code.pot
odoo/addons/partner_bank_sort_code/models/__init__.py
odoo/addons/partner_bank_sort_code/models/res_bank.py
odoo/addons/partner_bank_sort_code/readme/CONTRIBUTORS.rst
odoo/addons/partner_bank_sort_code/readme/DESCRIPTION.rst
odoo/addons/partner_bank_sort_code/readme/HISTORY.rst
odoo/addons/partner_bank_sort_code/readme/USAGE.rst
odoo/addons/partner_bank_sort_code/static/description/icon.png
odoo/addons/partner_bank_sort_code/static/description/index.html
odoo/addons/partner_bank_sort_code/tests/__init__.py
odoo/addons/partner_bank_sort_code/tests/test_sort_code.py
odoo/addons/partner_bank_sort_code/views/res_bank.xml
odoo13_addon_partner_bank_sort_code-13.0.1.0.1.dist-info/METADATA
odoo13_addon_partner_bank_sort_code-13.0.1.0.1.dist-info/WHEEL
odoo13_addon_partner_bank_sort_code-13.0.1.0.1.dist-info/top_level.txt
odoo13_addon_partner_bank_sort_code-13.0.1.0.1.dist-info/RECORD
